dming/__init__.py
dming/cli.py
dming/dice.py
dming-0.1.1.dist-info/METADATA
dming-0.1.1.dist-info/WHEEL
dming-0.1.1.dist-info/entry_points.txt
dming-0.1.1.dist-info/licenses/LICENSE
dming-0.1.1.dist-info/RECORD
