Metadata-Version: 2.4
Name: dming
Version: 0.1.1
Summary: DMing is a CLI (command-line interface) collection useful when running a TTRPG (tabletop role-playing games).
License: MIT
License-File: LICENSE
Author: Saúl Piña
Author-email: sauljabin@gmail.com
Requires-Python: >=3.13,<3.15
Classifier: License :: OSI Approved :: MIT License
Classifier: Environment :: Console
Classifier: Operating System :: MacOS
Classifier: Operating System :: Unix
Classifier: Programming Language :: Python :: 3.13
Classifier: Programming Language :: Python :: 3.14
Requires-Dist: click (>=8)
Requires-Dist: rich (>=14)
